ai_data_prep/__init__.py
ai_data_prep/preprocessing.py
ai_data_prep-0.1.0.dist-info/METADATA
ai_data_prep-0.1.0.dist-info/WHEEL
ai_data_prep-0.1.0.dist-info/top_level.txt
ai_data_prep-0.1.0.dist-info/RECORD
